{
    "questions": [
        {
            "id": 1,
            "text": "How often do you have trouble wrapping up the final details of a project, once the challenging parts have been done?",
            "options": [
                "Never",
                "Rarely",
                "Sometimes",
                "Often",
                "Very Often"
            ],
            "explanation": "Do you find it hard to finish the last steps of a task, even after completing the difficult parts?"
        },
        {
            "id": 2,
            "text": "How often do you have difficulty getting things in order when you have to do a task that requires organisation?",
            "options": [
                "Never",
                "Rarely",
                "Sometimes",
                "Often",
                "Very Often"
            ],
            "explanation": "Is it challenging for you to organize tasks that need planning and structure?"
        },
        {
            "id": 3,
            "text": "How often do you have problems remembering appointments or obligations?",
            "options": [
                "Never",
                "Rarely",
                "Sometimes",
                "Often",
                "Very Often"
            ],
            "explanation": "Do you often forget meetings or things you promised to do?"
        },
        {
            "id": 4,
            "text": "When you have a task that requires a lot of thought, how often do you avoid or delay getting started?",
            "options": [
                "Never",
                "Rarely",
                "Sometimes",
                "Often",
                "Very Often"
            ],
            "explanation": "Do you put off starting tasks that need deep thinking?"
        },
        {
            "id": 5,
            "text": "How often do you fidget or squirm with your hands or feet when you have to sit down for a long time?",
            "options": [
                "Never",
                "Rarely",
                "Sometimes",
                "Often",
                "Very Often"
            ],
            "explanation": "Do you feel restless or move around when sitting for extended periods?"
        },
        {
            "id": 6,
            "text": "How often do you feel overly active and compelled to do things, like you were driven by a motor?",
            "options": [
                "Never",
                "Rarely",
                "Sometimes",
                "Often",
                "Very Often"
            ],
            "explanation": "Do you feel like you're always on the go, as if driven by a motor?"
        },
        {
            "id": 7,
            "text": "How often do you make careless mistakes when you have to work on a boring or difficult project?",
            "options": [
                "Never",
                "Rarely",
                "Sometimes",
                "Often",
                "Very Often"
            ],
            "explanation": "Do you make simple mistakes when tasks are dull or challenging?"
        },
        {
            "id": 8,
            "text": "How often do you have difficulty keeping your attention when you are doing boring or repetitive work?",
            "options": [
                "Never",
                "Rarely",
                "Sometimes",
                "Often",
                "Very Often"
            ],
            "explanation": "Is it hard for you to stay focused on tasks that are monotonous or repetitive?"
        },
        {
            "id": 9,
            "text": "How often do you have difficulty keeping your attention when you are doing boring or repetitive work?",
            "options": [
                "Never",
                "Rarely",
                "Sometimes",
                "Often",
                "Very Often"
            ],
            "explanation": "Do you struggle to maintain attention during tasks that lack excitement or variety?"
        },
        {
            "id": 10,
            "text": "How often do you have difficulty concentrating on what people say to you, even when they are speaking to you directly?",
            "options": [
                "Never",
                "Rarely",
                "Sometimes",
                "Often",
                "Very Often"
            ],
            "explanation": "Do you find it hard to focus on conversations, even when someone is speaking directly to you?"
        },
        {
            "id": 11,
            "text": "How often do you misplace or have difficulty finding things at home or at work?",
            "options": [
                "Never",
                "Rarely",
                "Sometimes",
                "Often",
                "Very Often"
            ],
            "explanation": "Do you frequently lose or have trouble locating items in your home or workplace?"
        },
        {
            "id": 12,
            "text": "How often do you leave your seat in meetings or other situations in which you are expected to remain seated?",
            "options": [
                "Never",
                "Rarely",
                "Sometimes",
                "Often",
                "Very Often"
            ],
            "explanation": "Do you often get up during meetings or situations where you're supposed to stay seated?"
        },
        {
            "id": 13,
            "text": "How often do you feel restless or fidgety?",
            "options": [
                "Never",
                "Rarely",
                "Sometimes",
                "Often",
                "Very Often"
            ],
            "explanation": "Do you frequently feel the need to move or can't sit still?"
        },
        {
            "id": 14,
            "text": "How often do you have difficulty unwinding and relaxing when you have time to yourself?",
            "options": [
                "Never",
                "Rarely",
                "Sometimes",
                "Often",
                "Very Often"
            ],
            "explanation": "Is it hard for you to relax and unwind during your free time?"
        },
        {
            "id": 15,
            "text": "How often do you find yourself talking too much when you are in social situations?",
            "options": [
                "Never",
                "Rarely",
                "Sometimes",
                "Often",
                "Very Often"
            ],
            "explanation": "Do you tend to talk excessively in social settings?"
        },
        {
            "id": 16,
            "text": "When you're in a conversation, how often do you find yourself finishing the sentences of the people you are talking to, before they can finish them themselves?",
            "options": [
                "Never",
                "Rarely",
                "Sometimes",
                "Often",
                "Very Often"
            ],
            "explanation": "Do you often complete other people's sentences during conversations?"
        },
        {
            "id": 17,
            "text": "How often do you have difficulty waiting your turn in situations when turn taking is required?",
            "options": [
                "Never",
                "Rarely",
                "Sometimes",
                "Often",
                "Very Often"
            ],
            "explanation": "Is waiting your turn in lines or group activities challenging for you?"
        },
        {
            "id": 18,
            "text": "How often do you interrupt others when they are busy?",
            "options": [
                "Never",
                "Rarely",
                "Sometimes",
                "Often",
                "Very Often"
            ],
            "explanation": "Do you frequently interrupt people when they're occupied or engaged in tasks?"
        }
    ]
}